netlist2ss/__init__.py
netlist2ss/netlist2ss.py
netlist2ss/sisotf.py
netlist2ss-0.2.1.dist-info/LICENSE
netlist2ss-0.2.1.dist-info/METADATA
netlist2ss-0.2.1.dist-info/WHEEL
netlist2ss-0.2.1.dist-info/entry_points.txt
netlist2ss-0.2.1.dist-info/top_level.txt
netlist2ss-0.2.1.dist-info/RECORD
