Metadata-Version: 2.1
Name: netlist2ss
Version: 0.2.1
Summary: A package to convert spice netlist into space state representation
Author-email: Rodrigo Pedroso Mendes <roedroso@gmail.com>
Project-URL: Homepage, https://github.com/rpm2003rpm/netlist2ss
Classifier: Programming Language :: Python :: 3
Classifier: License :: OSI Approved :: MIT License
Classifier: Operating System :: OS Independent
Requires-Python: >=3.7
License-File: LICENSE
Requires-Dist: numpy (>=1.25.2)
Requires-Dist: regex (>=2023.6.3)
Requires-Dist: sympy (>=1.11.1)
